aurora_dsql_sqlalchemy/README.md
aurora_dsql_sqlalchemy/__init__.py
aurora_dsql_sqlalchemy/_version.py
aurora_dsql_sqlalchemy/base.py
aurora_dsql_sqlalchemy/psycopg.py
aurora_dsql_sqlalchemy/psycopg2.py
aurora_dsql_sqlalchemy-1.1.3.dist-info/METADATA
aurora_dsql_sqlalchemy-1.1.3.dist-info/WHEEL
aurora_dsql_sqlalchemy-1.1.3.dist-info/entry_points.txt
aurora_dsql_sqlalchemy-1.1.3.dist-info/RECORD
