Metadata-Version: 2.4
Name: aurora-dsql-sqlalchemy
Version: 1.1.3
Summary: Amazon Aurora DSQL dialect for SQLAlchemy
Project-URL: Repository, https://github.com/awslabs/aurora-dsql-orms
Project-URL: Documentation, https://github.com/awslabs/aurora-dsql-orms/tree/main/python/sqlalchemy
Author: Amazon Web Services
License-Expression: Apache-2.0
Classifier: Intended Audience :: Developers
Classifier: License :: OSI Approved :: Apache Software License
Classifier: Programming Language :: Python
Classifier: Programming Language :: Python :: 3.10
Classifier: Programming Language :: Python :: 3.11
Classifier: Programming Language :: Python :: 3.12
Classifier: Programming Language :: Python :: 3.13
Requires-Python: >=3.10
Requires-Dist: aurora-dsql-python-connector>=0.1.0
Requires-Dist: sqlalchemy>=2.0.0
Provides-Extra: psycopg
Requires-Dist: psycopg[binary]>=3.2.0; extra == 'psycopg'
Provides-Extra: psycopg2
Requires-Dist: psycopg2-binary>=2.9.0; extra == 'psycopg2'
